flake8_respect_noqa.py
flake8_respect_noqa-0.3.dist-info/RECORD
flake8_respect_noqa-0.3.dist-info/DESCRIPTION.rst
flake8_respect_noqa-0.3.dist-info/METADATA
flake8_respect_noqa-0.3.dist-info/top_level.txt
flake8_respect_noqa-0.3.dist-info/entry_points.txt
flake8_respect_noqa-0.3.dist-info/metadata.json
flake8_respect_noqa-0.3.dist-info/WHEEL
