Metadata-Version: 2.0
Name: flake8-respect-noqa
Version: 0.3
Summary: Always ignore #noqa lines with flake8.
Home-page: https://github.com/spookylukey/flake8-respect-noqa
Author: Luke Plant
Author-email: L.Plant.98@cantab.net
License: MIT
Keywords: flake8 noqa pep8
Platform: UNKNOWN
Classifier: Development Status :: 3 - Alpha
Classifier: Environment :: Console
Classifier: Intended Audience :: Developers
Classifier: License :: OSI Approved :: MIT License
Classifier: Operating System :: OS Independent
Classifier: Programming Language :: Python
Classifier: Programming Language :: Python :: 2
Classifier: Programming Language :: Python :: 3
Classifier: Topic :: Software Development :: Libraries :: Python Modules
Classifier: Topic :: Software Development :: Quality Assurance
Requires-Dist: flake8 (>=2.4.1)
